{
  "id": "2",
  "error": 2.3550484640899216,
  "resolution": {
    "height": 1080,
    "width": 1440
  },
  "intrinsic": {
    "shape": {
      "dims": [
        {
          "size": 3,
          "name": "rows"
        },
        {
          "size": 3,
          "name": "cols"
        }
      ]
    },
    "type": "DOUBLE_TYPE",
    "floats": [],
    "doubles": [
      1339.4290438826233,
      0.0,
      716.6819760496181,
      0.0,
      1320.2628097384807,
      564.5161864405896,
      0.0,
      0.0,
      1.0
    ],
    "ints32": [],
    "ints64": []
  },
  "distortion": {
    "shape": {
      "dims": [
        {
          "size": 1,
          "name": "rows"
        },
        {
          "size": 5,
          "name": "cols"
        }
      ]
    },
    "type": "DOUBLE_TYPE",
    "floats": [],
    "doubles": [
      -0.07437312481453207,
      -0.7297868016987427,
      -0.004921540683316445,
      0.013910113895750123,
      1.9345646136197243
    ],
    "ints32": [],
    "ints64": []
  },
  "extrinsic": [
    {
      "from": "1000",
      "to": "2",
      "tf": {
        "shape": {
          "dims": [
            {
              "size": 4,
              "name": "rows"
            },
            {
              "size": 4,
              "name": "cols"
            }
          ]
        },
        "type": "DOUBLE_TYPE",
        "floats": [],
        "doubles": [
          -0.8043968503431691,
          -0.5936890541540801,
          0.02188639156240349,
          0.03534929743135795,
          -0.3569316388532922,
          0.4535049969370284,
          -0.8166596738780781,
          0.5986739958951399,
          0.47491632141198536,
          -0.6647304150787593,
          -0.576704398219511,
          4.514443500344082,
          0.0,
          0.0,
          0.0,
          1.0
        ],
        "ints32": [],
        "ints64": []
      }
    }
  ],
  "calibratedAt": "2023-07-25T13:04:35Z"
}